mkdocs_strapi_plugin/__init__.py
mkdocs_strapi_plugin/cli.py
mkdocs_strapi_plugin/mkdocs_strapi_plugin.py
mkdocs_strapi_plugin-0.2.0.dist-info/AUTHORS.rst
mkdocs_strapi_plugin-0.2.0.dist-info/LICENSE
mkdocs_strapi_plugin-0.2.0.dist-info/METADATA
mkdocs_strapi_plugin-0.2.0.dist-info/WHEEL
mkdocs_strapi_plugin-0.2.0.dist-info/entry_points.txt
mkdocs_strapi_plugin-0.2.0.dist-info/top_level.txt
mkdocs_strapi_plugin-0.2.0.dist-info/RECORD
