Metadata-Version: 2.1
Name: mkdocs-strapi-plugin
Version: 0.2.0
Summary: This plugin is designed to fetch data from Strapi API and inject that data into the mkdocs.
Home-page: https://github.com/enecode/mkdocs_strapi_plugin
Author: Isah Jacob
Author-email: isahjacob0@gmail.com
License: Apache Software License 2.0
Keywords: mkdocs_strapi_plugin
Classifier: Development Status :: 2 - Pre-Alpha
Classifier: Intended Audience :: Developers
Classifier: License :: OSI Approved :: Apache Software License
Classifier: Natural Language :: English
Classifier: Programming Language :: Python :: 3
Classifier: Programming Language :: Python :: 3.6
Classifier: Programming Language :: Python :: 3.7
Classifier: Programming Language :: Python :: 3.8
Requires-Python: >=3.6
License-File: LICENSE
License-File: AUTHORS.rst
Requires-Dist: Click >=7.0
